CHANGES.rst
LICENCE.rst
README.rst
setup.py
src/collective/__init__.py
src/collective.wfeffectiverange.egg-info/PKG-INFO
src/collective.wfeffectiverange.egg-info/SOURCES.txt
src/collective.wfeffectiverange.egg-info/dependency_links.txt
src/collective.wfeffectiverange.egg-info/entry_points.txt
src/collective.wfeffectiverange.egg-info/namespace_packages.txt
src/collective.wfeffectiverange.egg-info/not-zip-safe
src/collective.wfeffectiverange.egg-info/requires.txt
src/collective.wfeffectiverange.egg-info/top_level.txt
src/collective/wfeffectiverange/__init__.py
src/collective/wfeffectiverange/behaviors.py
src/collective/wfeffectiverange/configure.zcml
src/collective/wfeffectiverange/indexers.py
src/collective/wfeffectiverange/setuphandlers.py
src/collective/wfeffectiverange/subscribers.py
src/collective/wfeffectiverange/upgrades.py
src/collective/wfeffectiverange/upgrades.zcml
src/collective/wfeffectiverange/vocabulary.py
src/collective/wfeffectiverange/browser/__init__.py
src/collective/wfeffectiverange/browser/configure.zcml
src/collective/wfeffectiverange/browser/views.py
src/collective/wfeffectiverange/browser/resources/wfeffectiverange-reload-vocab.js
src/collective/wfeffectiverange/locales/collective.wfeffectiverange.pot
src/collective/wfeffectiverange/locales/de/LC_MESSAGES/collective.wfeffectiverange.po
src/collective/wfeffectiverange/locales/en/LC_MESSAGES/collective.wfeffectiverange.po
src/collective/wfeffectiverange/profiles/base/catalog.xml
src/collective/wfeffectiverange/profiles/base/metadata.xml
src/collective/wfeffectiverange/profiles/plone4/jsregistry.xml
src/collective/wfeffectiverange/profiles/plone4/metadata.xml
src/collective/wfeffectiverange/profiles/plone5/metadata.xml
src/collective/wfeffectiverange/profiles/plone5/registry.xml
src/collective/wfeffectiverange/profiles/testing/metadata.xml
src/collective/wfeffectiverange/profiles/testing/types.xml
src/collective/wfeffectiverange/profiles/testing/types/WFEffectiveRangeExample.xml